setup.py
geocodio/__init__.py
geocodio/client.py
geocodio.egg-info/PKG-INFO
geocodio.egg-info/SOURCES.txt
geocodio.egg-info/dependency_links.txt
geocodio.egg-info/not-zip-safe
geocodio.egg-info/requires.txt
geocodio.egg-info/top_level.txt