Metadata-Version: 1.1
Name: geocodio
Version: 1.0.0
Summary: Simple wrapper for geocod.io address service
Home-page: https://github.com/davidstanley01/geocodio.py
Author: David Stanley
Author-email: davidstanley01@gmail.com
License: BSD License
Platform: UNKNOWN
Classifier: Environment :: Web Environment
Classifier: Intended Audience :: Developers
Classifier: License :: OSI Approved :: BSD License
Classifier: Operating System :: OS Independent
Classifier: Programming Language :: Python
Classifier: Topic :: Utilities
